funcparse
