Metadata-Version: 1.1
Name: funcparse
Version: 1.0.2
Summary: Parse `funcname`, `args`, `kargs` from function-like string
Home-page: https://github.com/sjquant/funcparse
Author: SJQuant
Author-email: seonujang92@gmail.com
License: MIT
Keywords: parse,parse function,string-to-function
Platform: UNKNOWN
Classifier: Programming Language :: Python :: 3
Classifier: License :: OSI Approved :: MIT License
Classifier: Operating System :: OS Independent
